<?xml version="1.0" encoding="UTF-8" standalone="yes"?>
<p:sld xmlns:a="http://schemas.openxmlformats.org/drawingml/2006/main" xmlns:r="http://schemas.openxmlformats.org/officeDocument/2006/relationships" xmlns:p="http://schemas.openxmlformats.org/presentationml/2006/main"><p:cSld><p:spTree><p:nvGrpSpPr><p:cNvPr id="1" name="Shape 284"/><p:cNvGrpSpPr/><p:nvPr/></p:nvGrpSpPr><p:grpSpPr><a:xfrm><a:off x="0" y="0"/><a:ext cx="0" cy="0"/><a:chOff x="0" y="0"/><a:chExt cx="0" cy="0"/></a:xfrm></p:grpSpPr><p:sp><p:nvSpPr><p:cNvPr id="285" name="Google Shape;285;p25"/><p:cNvSpPr txBox="1"><a:spLocks noGrp="1"/></p:cNvSpPr><p:nvPr><p:ph type="body" idx="1"/></p:nvPr></p:nvSpPr><p:spPr><a:xfrm><a:off x="723900" y="2105025"/><a:ext cx="1666800" cy="723900"/></a:xfrm><a:prstGeom prst="rect"><a:avLst/></a:prstGeom><a:noFill/><a:ln><a:noFill/></a:ln></p:spPr><p:txBody><a:bodyPr spcFirstLastPara="1" wrap="square" lIns="0" tIns="0" rIns="0" bIns="0" anchor="ctr" anchorCtr="0"><a:normAutofit/></a:bodyPr><a:lstStyle/><a:p><a:pPr marL="0" lvl="0" indent="0" algn="ctr" rtl="0"><a:lnSpc><a:spcPct val="127500"/></a:lnSpc><a:spcBef><a:spcPts val="0"/></a:spcBef><a:spcAft><a:spcPts val="0"/></a:spcAft><a:buClr><a:srgbClr val="206E8C"/></a:buClr><a:buSzPts val="900"/><a:buNone/></a:pPr><a:r><a:rPr lang="en" sz="900" b="1"><a:solidFill><a:srgbClr val="206E8C"/></a:solidFill><a:latin typeface="Roboto"/><a:ea typeface="Roboto"/><a:cs typeface="Roboto"/><a:sym typeface="Roboto"/></a:rPr><a:t>Info sheets for all certificates and categories, customizable with your logo and website URL</a:t></a:r><a:endParaRPr sz="900"/></a:p></p:txBody></p:sp><p:sp><p:nvSpPr><p:cNvPr id="286" name="Google Shape;286;p25"/><p:cNvSpPr txBox="1"><a:spLocks noGrp="1"/></p:cNvSpPr><p:nvPr><p:ph type="body" idx="2"/></p:nvPr></p:nvSpPr><p:spPr><a:xfrm><a:off x="2733675" y="2105025"/><a:ext cx="1666800" cy="723900"/></a:xfrm><a:prstGeom prst="rect"><a:avLst/></a:prstGeom><a:noFill/><a:ln><a:noFill/></a:ln></p:spPr><p:txBody><a:bodyPr spcFirstLastPara="1" wrap="square" lIns="0" tIns="0" rIns="0" bIns="0" anchor="ctr" anchorCtr="0"><a:normAutofit/></a:bodyPr><a:lstStyle/><a:p><a:pPr marL="0" lvl="0" indent="0" algn="ctr" rtl="0"><a:lnSpc><a:spcPct val="127500"/></a:lnSpc><a:spcBef><a:spcPts val="0"/></a:spcBef><a:spcAft><a:spcPts val="0"/></a:spcAft><a:buClr><a:srgbClr val="206E8C"/></a:buClr><a:buSzPts val="900"/><a:buNone/></a:pPr><a:r><a:rPr lang="en" sz="900" b="1"><a:solidFill><a:srgbClr val="206E8C"/></a:solidFill><a:latin typeface="Roboto"/><a:ea typeface="Roboto"/><a:cs typeface="Roboto"/><a:sym typeface="Roboto"/></a:rPr><a:t>Promotional info videos</a:t></a:r><a:endParaRPr sz="900"/></a:p></p:txBody></p:sp><p:sp><p:nvSpPr><p:cNvPr id="287" name="Google Shape;287;p25"/><p:cNvSpPr txBox="1"><a:spLocks noGrp="1"/></p:cNvSpPr><p:nvPr><p:ph type="body" idx="3"/></p:nvPr></p:nvSpPr><p:spPr><a:xfrm><a:off x="4743450" y="2105025"/><a:ext cx="1666800" cy="723900"/></a:xfrm><a:prstGeom prst="rect"><a:avLst/></a:prstGeom><a:noFill/><a:ln><a:noFill/></a:ln></p:spPr><p:txBody><a:bodyPr spcFirstLastPara="1" wrap="square" lIns="0" tIns="0" rIns="0" bIns="0" anchor="ctr" anchorCtr="0"><a:normAutofit/></a:bodyPr><a:lstStyle/><a:p><a:pPr marL="0" lvl="0" indent="0" algn="ctr" rtl="0"><a:lnSpc><a:spcPct val="127500"/></a:lnSpc><a:spcBef><a:spcPts val="0"/></a:spcBef><a:spcAft><a:spcPts val="0"/></a:spcAft><a:buClr><a:srgbClr val="206E8C"/></a:buClr><a:buSzPts val="900"/><a:buNone/></a:pPr><a:r><a:rPr lang="en" sz="900" b="1"><a:solidFill><a:srgbClr val="206E8C"/></a:solidFill><a:latin typeface="Roboto"/><a:ea typeface="Roboto"/><a:cs typeface="Roboto"/><a:sym typeface="Roboto"/></a:rPr><a:t>HTML links for email marketing</a:t></a:r><a:endParaRPr sz="900"/></a:p></p:txBody></p:sp><p:sp><p:nvSpPr><p:cNvPr id="288" name="Google Shape;288;p25"/><p:cNvSpPr txBox="1"><a:spLocks noGrp="1"/></p:cNvSpPr><p:nvPr><p:ph type="body" idx="4"/></p:nvPr></p:nvSpPr><p:spPr><a:xfrm><a:off x="6753225" y="2105025"/><a:ext cx="1666800" cy="723900"/></a:xfrm><a:prstGeom prst="rect"><a:avLst/></a:prstGeom><a:noFill/><a:ln><a:noFill/></a:ln></p:spPr><p:txBody><a:bodyPr spcFirstLastPara="1" wrap="square" lIns="0" tIns="0" rIns="0" bIns="0" anchor="ctr" anchorCtr="0"><a:normAutofit/></a:bodyPr><a:lstStyle/><a:p><a:pPr marL="0" lvl="0" indent="0" algn="ctr" rtl="0"><a:lnSpc><a:spcPct val="127500"/></a:lnSpc><a:spcBef><a:spcPts val="0"/></a:spcBef><a:spcAft><a:spcPts val="0"/></a:spcAft><a:buClr><a:srgbClr val="206E8C"/></a:buClr><a:buSzPts val="900"/><a:buNone/></a:pPr><a:r><a:rPr lang="en" sz="900" b="1"><a:solidFill><a:srgbClr val="206E8C"/></a:solidFill><a:latin typeface="Roboto"/><a:ea typeface="Roboto"/><a:cs typeface="Roboto"/><a:sym typeface="Roboto"/></a:rPr><a:t>Best practices</a:t></a:r><a:endParaRPr sz="900"/></a:p></p:txBody></p:sp><p:sp><p:nvSpPr><p:cNvPr id="289" name="Google Shape;289;p25"/><p:cNvSpPr txBox="1"><a:spLocks noGrp="1"/></p:cNvSpPr><p:nvPr><p:ph type="body" idx="5"/></p:nvPr></p:nvSpPr><p:spPr><a:xfrm><a:off x="723900" y="3171825"/><a:ext cx="1666800" cy="723900"/></a:xfrm><a:prstGeom prst="rect"><a:avLst/></a:prstGeom><a:noFill/><a:ln><a:noFill/></a:ln></p:spPr><p:txBody><a:bodyPr spcFirstLastPara="1" wrap="square" lIns="0" tIns="0" rIns="0" bIns="0" anchor="ctr" anchorCtr="0"><a:normAutofit/></a:bodyPr><a:lstStyle/><a:p><a:pPr marL="0" lvl="0" indent="0" algn="ctr" rtl="0"><a:lnSpc><a:spcPct val="127500"/></a:lnSpc><a:spcBef><a:spcPts val="0"/></a:spcBef><a:spcAft><a:spcPts val="0"/></a:spcAft><a:buClr><a:srgbClr val="206E8C"/></a:buClr><a:buSzPts val="900"/><a:buNone/></a:pPr><a:r><a:rPr lang="en" sz="900" b="1"><a:solidFill><a:srgbClr val="206E8C"/></a:solidFill><a:latin typeface="Roboto"/><a:ea typeface="Roboto"/><a:cs typeface="Roboto"/><a:sym typeface="Roboto"/></a:rPr><a:t>Success stories</a:t></a:r><a:endParaRPr sz="900"/></a:p></p:txBody></p:sp><p:sp><p:nvSpPr><p:cNvPr id="290" name="Google Shape;290;p25"/><p:cNvSpPr txBox="1"><a:spLocks noGrp="1"/></p:cNvSpPr><p:nvPr><p:ph type="body" idx="6"/></p:nvPr></p:nvSpPr><p:spPr><a:xfrm><a:off x="2733675" y="3171825"/><a:ext cx="1666800" cy="723900"/></a:xfrm><a:prstGeom prst="rect"><a:avLst/></a:prstGeom><a:noFill/><a:ln><a:noFill/></a:ln></p:spPr><p:txBody><a:bodyPr spcFirstLastPara="1" wrap="square" lIns="0" tIns="0" rIns="0" bIns="0" anchor="ctr" anchorCtr="0"><a:normAutofit/></a:bodyPr><a:lstStyle/><a:p><a:pPr marL="0" lvl="0" indent="0" algn="ctr" rtl="0"><a:lnSpc><a:spcPct val="127500"/></a:lnSpc><a:spcBef><a:spcPts val="0"/></a:spcBef><a:spcAft><a:spcPts val="0"/></a:spcAft><a:buClr><a:srgbClr val="206E8C"/></a:buClr><a:buSzPts val="900"/><a:buNone/></a:pPr><a:r><a:rPr lang="en" sz="900" b="1"><a:solidFill><a:srgbClr val="206E8C"/></a:solidFill><a:latin typeface="Roboto"/><a:ea typeface="Roboto"/><a:cs typeface="Roboto"/><a:sym typeface="Roboto"/></a:rPr><a:t>Reports on sales trends</a:t></a:r><a:endParaRPr sz="900"/></a:p></p:txBody></p:sp><p:sp><p:nvSpPr><p:cNvPr id="291" name="Google Shape;291;p25"/><p:cNvSpPr txBox="1"><a:spLocks noGrp="1"/></p:cNvSpPr><p:nvPr><p:ph type="body" idx="7"/></p:nvPr></p:nvSpPr><p:spPr><a:xfrm><a:off x="4743475" y="3172575"/><a:ext cx="1666800" cy="722400"/></a:xfrm><a:prstGeom prst="rect"><a:avLst/></a:prstGeom><a:noFill/><a:ln><a:noFill/></a:ln></p:spPr><p:txBody><a:bodyPr spcFirstLastPara="1" wrap="square" lIns="0" tIns="0" rIns="0" bIns="0" anchor="ctr" anchorCtr="0"><a:noAutofit/></a:bodyPr><a:lstStyle/><a:p><a:pPr marL="0" lvl="0" indent="0" algn="ctr" rtl="0"><a:lnSpc><a:spcPct val="127500"/></a:lnSpc><a:spcBef><a:spcPts val="0"/></a:spcBef><a:spcAft><a:spcPts val="0"/></a:spcAft><a:buClr><a:srgbClr val="206E8C"/></a:buClr><a:buSzPts val="900"/><a:buNone/></a:pPr><a:r><a:rPr lang="en" sz="900" b="1"><a:solidFill><a:srgbClr val="206E8C"/></a:solidFill><a:latin typeface="Roboto"/><a:ea typeface="Roboto"/><a:cs typeface="Roboto"/><a:sym typeface="Roboto"/></a:rPr><a:t>Social text and images to promote the top-selling certificates</a:t></a:r><a:endParaRPr sz="900"/></a:p></p:txBody></p:sp><p:sp><p:nvSpPr><p:cNvPr id="292" name="Google Shape;292;p25"/><p:cNvSpPr txBox="1"><a:spLocks noGrp="1"/></p:cNvSpPr><p:nvPr><p:ph type="body" idx="8"/></p:nvPr></p:nvSpPr><p:spPr><a:xfrm><a:off x="609600" y="1257300"/><a:ext cx="7924800" cy="385200"/></a:xfrm><a:prstGeom prst="rect"><a:avLst/></a:prstGeom><a:noFill/><a:ln><a:noFill/></a:ln></p:spPr><p:txBody><a:bodyPr spcFirstLastPara="1" wrap="square" lIns="0" tIns="0" rIns="0" bIns="0" anchor="t" anchorCtr="0"><a:spAutoFit/></a:bodyPr><a:lstStyle/><a:p><a:pPr marL="0" lvl="0" indent="0" algn="l" rtl="0"><a:lnSpc><a:spcPct val="127511"/></a:lnSpc><a:spcBef><a:spcPts val="0"/></a:spcBef><a:spcAft><a:spcPts val="0"/></a:spcAft><a:buClr><a:srgbClr val="1A1D1E"/></a:buClr><a:buSzPts val="1100"/><a:buNone/></a:pPr><a:r><a:rPr lang="en" sz="1100" i="1"><a:solidFill><a:srgbClr val="1A1D1E"/></a:solidFill><a:latin typeface="Roboto"/><a:ea typeface="Roboto"/><a:cs typeface="Roboto"/><a:sym typeface="Roboto"/></a:rPr><a:t>We are pleased to provide our partners with a comprehensive resource center of customizable assets to help in your marketing efforts:</a:t></a:r><a:endParaRPr sz="1100"/></a:p></p:txBody></p:sp><p:sp><p:nvSpPr><p:cNvPr id="293" name="Google Shape;293;p25"/><p:cNvSpPr txBox="1"><a:spLocks noGrp="1"/></p:cNvSpPr><p:nvPr><p:ph type="body" idx="9"/></p:nvPr></p:nvSpPr><p:spPr><a:xfrm><a:off x="611900" y="619275"/><a:ext cx="7920300" cy="369300"/></a:xfrm><a:prstGeom prst="rect"><a:avLst/></a:prstGeom><a:noFill/><a:ln><a:noFill/></a:ln></p:spPr><p:txBody><a:bodyPr spcFirstLastPara="1" wrap="square" lIns="0" tIns="0" rIns="0" bIns="0" anchor="t" anchorCtr="0"><a:spAutoFit/></a:bodyPr><a:lstStyle/><a:p><a:pPr marL="0" lvl="0" indent="0" algn="l" rtl="0"><a:lnSpc><a:spcPct val="102000"/></a:lnSpc><a:spcBef><a:spcPts val="0"/></a:spcBef><a:spcAft><a:spcPts val="0"/></a:spcAft><a:buClr><a:srgbClr val="206E8C"/></a:buClr><a:buSzPts val="2300"/><a:buNone/></a:pPr><a:r><a:rPr lang="en" b="1"><a:solidFill><a:srgbClr val="206E8C"/></a:solidFill><a:latin typeface="Roboto"/><a:ea typeface="Roboto"/><a:cs typeface="Roboto"/><a:sym typeface="Roboto"/></a:rPr><a:t>Marketing Resource Center</a:t></a:r><a:endParaRPr/></a:p></p:txBody></p:sp><p:sp><p:nvSpPr><p:cNvPr id="294" name="Google Shape;294;p25"/><p:cNvSpPr txBox="1"><a:spLocks noGrp="1"/></p:cNvSpPr><p:nvPr><p:ph type="body" idx="13"/></p:nvPr></p:nvSpPr><p:spPr><a:xfrm><a:off x="611900" y="447675"/><a:ext cx="7920300" cy="171600"/></a:xfrm><a:prstGeom prst="rect"><a:avLst/></a:prstGeom><a:noFill/><a:ln><a:noFill/></a:ln></p:spPr><p:txBody><a:bodyPr spcFirstLastPara="1" wrap="square" lIns="0" tIns="0" rIns="0" bIns="0" anchor="b" anchorCtr="0"><a:noAutofit/></a:bodyPr><a:lstStyle/><a:p><a:pPr marL="0" lvl="0" indent="0" algn="l" rtl="0"><a:lnSpc><a:spcPct val="127500"/></a:lnSpc><a:spcBef><a:spcPts val="0"/></a:spcBef><a:spcAft><a:spcPts val="0"/></a:spcAft><a:buClr><a:srgbClr val="1A1D1E"/></a:buClr><a:buSzPts val="900"/><a:buNone/></a:pPr><a:r><a:rPr lang="en" sz="900" b="1"><a:solidFill><a:srgbClr val="1A1D1E"/></a:solidFill><a:latin typeface="Roboto"/><a:ea typeface="Roboto"/><a:cs typeface="Roboto"/><a:sym typeface="Roboto"/></a:rPr><a:t>What We Provide</a:t></a:r><a:endParaRPr sz="900"/></a:p></p:txBody></p:sp></p:spTree></p:cSld><p:clrMapOvr><a:masterClrMapping/></p:clrMapOvr></p:sld>